pydantic_settings/__init__.py
pydantic_settings/exceptions.py
pydantic_settings/main.py
pydantic_settings/py.typed
pydantic_settings/utils.py
pydantic_settings/version.py
pydantic_settings/sources/__init__.py
pydantic_settings/sources/base.py
pydantic_settings/sources/types.py
pydantic_settings/sources/utils.py
pydantic_settings/sources/providers/__init__.py
pydantic_settings/sources/providers/aws.py
pydantic_settings/sources/providers/azure.py
pydantic_settings/sources/providers/cli.py
pydantic_settings/sources/providers/dotenv.py
pydantic_settings/sources/providers/env.py
pydantic_settings/sources/providers/gcp.py
pydantic_settings/sources/providers/json.py
pydantic_settings/sources/providers/pyproject.py
pydantic_settings/sources/providers/secrets.py
pydantic_settings/sources/providers/toml.py
pydantic_settings/sources/providers/yaml.py
pydantic_settings_qpython-2.9.1.dist-info/METADATA
pydantic_settings_qpython-2.9.1.dist-info/WHEEL
pydantic_settings_qpython-2.9.1.dist-info/top_level.txt
pydantic_settings_qpython-2.9.1.dist-info/RECORD
