Metadata-Version: 2.4
Name: pydantic-settings-qpython
Version: 2.9.1
Summary: Settings management using Pydantic
Home-page: https://pypi.org/project/pydantic-settings/
Author: The QPYPI Team
Author-email: qpypi@qpython.org
License: OSI Approved :: MIT License
Classifier: Intended Audience :: Developers
Classifier: Intended Audience :: Education
Classifier: Intended Audience :: Information Technology
Classifier: Intended Audience :: End Users/Desktop
Classifier: License :: OSI Approved :: Apache Software License
Classifier: Operating System :: Android
Classifier: Programming Language :: Python
Classifier: Programming Language :: Python :: 3.12
Classifier: Topic :: Software Development
Requires-Dist: pydantic-qpython
Requires-Dist: python-dotenv>=0.21.0
Requires-Dist: typing-inspection>=0.4.0
Dynamic: author
Dynamic: author-email
Dynamic: classifier
Dynamic: description
Dynamic: home-page
Dynamic: license
Dynamic: requires-dist
Dynamic: summary
